examples/__init__.py
examples/custom_variables.py
examples/load_mcmc.py
examples/plot_triangle.py
examples/simpleplots.py
examples/testchaindata.root
numcmctools/__init__.py
numcmctools/empirical_priors.py
numcmctools/jacobiangraph.py
numcmctools/mcmcsamples.py
numcmctools/plot.py
numcmctools/plotstack.py
numcmctools/variable.py
numcmctools-1.1.0.dist-info/licenses/LICENSE
numcmctools-1.1.0.dist-info/METADATA
numcmctools-1.1.0.dist-info/WHEEL
numcmctools-1.1.0.dist-info/entry_points.txt
numcmctools-1.1.0.dist-info/top_level.txt
numcmctools-1.1.0.dist-info/RECORD
