Metadata-Version: 2.4
Name: numcmctools
Version: 1.1.0
Summary: MCMC plotting framework for official results from neutrino oscillation experiments
Author-email: Asher Kaboth <Asher.Kaboth@rhul.ac.uk>, Artur Sztuc <a.sztuc@ucl.ac.uk>
Maintainer-email: Asher Kaboth <Asher.Kaboth@rhul.ac.uk>, Artur Sztuc <a.sztuc@ucl.ac.uk>
License: MIT License
Project-URL: Homepage, https://github.com/NuMCMCTools/NuMCMCTools
Project-URL: Documentation, https://github.com/NuMCMCTools/NuMCMCTools/blob/main/README.md
Project-URL: Repository, https://github.com/NuMCMCTools/NuMCMCTools.git
Project-URL: Issues, https://github.com/NuMCMCTools/NuMCMCTools/issues
Keywords: neutrino,physics,HEP,MCMC,plotting
Classifier: Development Status :: 4 - Beta
Classifier: Intended Audience :: Science/Research
Classifier: License :: OSI Approved :: MIT License
Classifier: Programming Language :: Python
Classifier: Programming Language :: Python :: 3
Classifier: Programming Language :: Python :: 3.7
Classifier: Programming Language :: Python :: 3.8
Classifier: Programming Language :: Python :: 3.9
Classifier: Programming Language :: Python :: 3.10
Classifier: Programming Language :: Python :: 3.11
Classifier: Programming Language :: Python :: 3.12
Classifier: Programming Language :: Python :: 3.13
Classifier: Programming Language :: Python :: 3.14
Classifier: Programming Language :: Python :: 3 :: Only
Classifier: Topic :: Scientific/Engineering :: Physics
Classifier: Operating System :: OS Independent
Requires-Python: >=3.8
License-File: LICENSE
Requires-Dist: numpy
Requires-Dist: matplotlib
Requires-Dist: sympy
Requires-Dist: tqdm
Requires-Dist: uproot
Requires-Dist: scipy
Dynamic: license-file
